BitSampleCount_transmit.sv

///////////////////////////////////////////////////////////////////////////////
// Module: BitSampleCounter.sv
// Project: Extending a Simple Microprocessor
// References:
// Description: Counter for char detection.
// Implmentation: Implemented in behavioral verilog.
//
// TODO: Data is not being sent out. Check If else logic.
// Change history:
//
///////////////////////////////////////////////////////////////////////////////

module BitSampleCounter_transmit(output SROut,
                        output idEnable,
                        input enable,
                        input clk,
                        input rst);

    reg [3:0] count;
    reg startFlag;
    reg id;
    reg SRControl;

    always @(posedge clk) begin
        if (!rst) begin
            count <= 4'b000;
            SRControl <= 1'b0;
            id <= 1'b0;
        end else begin
            if (enable == 0 && ~startFlag) begin
                startFlag <= 1'b1;
                SRControl <= 0;
                id <= 0;
            end else if (startFlag && (count < 4'b1111)) begin
                startFlag <= 1'b1;
                count <= count + 1;

                if (count == 4'b0111) begin
                    SRControl <= 1'b1;
                end else begin
                    SRControl <= 0;
                end
            end else begin
                SRControl <= 1'b0;
                id <= 1'b1;
                count <= 4'b0000;
                startFlag <= 1'b0;

            end
        end
    end

    assign idEnable = id;
    assign SROut = SRControl;

endmodule

module BitSampleCounter_transmit_tb();
    // Inputs
    reg enable;
    reg clk;
    reg rst;

    // Outputs
    wire SROut;
    wire idEnable;

    BitSampleCounter_transmit bsc(dataOut,
                         idEnable,
                         enable,
                         clk,
                         rst);

    initial begin
    $dumpfile("BitSampleCounter_transmit_tb.vcd");
    $dumpvars;
    end
    // Set up the clock.
    parameter CLOCK_PERIOD=2;
    initial clk=1;
    initial enable = 0;
    always begin
       #(CLOCK_PERIOD/2);
       clk = ~clk;
    end

    // Set up the inputs to the design. Each line is a clock cycle.
    initial begin
    rst <= 0; @(posedge clk)
    rst <= 1; @(posedge clk)

    enable <= 1; @(posedge clk)
    enable <= 0; @(posedge clk)
    @(posedge clk)
    @(posedge clk)
    @(posedge clk)
    @(posedge clk)
    @(posedge clk)
    @(posedge clk)
    @(posedge clk)
    @(posedge clk)
    @(posedge clk)
    @(posedge clk)
    @(posedge clk)
    @(posedge clk)
    @(posedge clk)
    @(posedge clk)
    @(posedge clk)
    @(posedge clk)
    @(posedge clk)
    @(posedge clk)
    @(posedge clk)
    @(posedge clk)
    @(posedge clk)
    @(posedge clk)
    @(posedge clk)
    @(posedge clk)
    @(posedge clk)
    @(posedge clk)
    @(posedge clk)
    @(posedge clk)
    @(posedge clk)

    $finish;
    end
endmodule

BitSampleCounter_transmit_tb.vcd
$date
	Tue May 24 17:44:49 2016
$end
$version
	Icarus Verilog
$end
$timescale
	1s
$end
$scope module BitSampleCounter_transmit_tb $end
$var wire 1 ! idEnable $end
$var wire 1 " dataOut $end
$var reg 1 # clk $end
$var reg 1 $ enable $end
$var reg 1 % rst $end
$scope module bsc $end
$var wire 1 " SROut $end
$var wire 1 # clk $end
$var wire 1 $ enable $end
$var wire 1 ! idEnable $end
$var wire 1 % rst $end
$var reg 1 & SRControl $end
$var reg 4 ' count [3:0] $end
$var reg 1 ( id $end
$var reg 1 ) startFlag $end
$upscope $end
$upscope $end
$enddefinitions $end
#0
$dumpvars
0)
1(
b0 '
0&
0%
0$
1#
0"
1!
$end
#1
0#
#2
1%
0!
0(
1#
#3
0#
#4
1)
1$
1#
#5
0#
#6
0$
b1 '
1#
#7
0#
#8
b10 '
1#
#9
0#
#10
b11 '
1#
#11
0#
#12
b100 '
1#
#13
0#
#14
b101 '
1#
#15
0#
#16
b110 '
1#
#17
0#
#18
b111 '
1#
#19
0#
#20
1"
1&
b1000 '
1#
#21
0#
#22
0"
0&
b1001 '
1#
#23
0#
#24
b1010 '
1#
#25
0#
#26
b1011 '
1#
#27
0#
#28
b1100 '
1#
#29
0#
#30
b1101 '
1#
#31
0#
#32
b1110 '
1#
#33
0#
#34
b1111 '
1#
#35
0#
#36
0)
b0 '
1!
1(
1#
#37
0#
#38
0!
0(
1)
1#
#39
0#
#40
b1 '
1#
#41
0#
#42
b10 '
1#
#43
0#
#44
b11 '
1#
#45
0#
#46
b100 '
1#
#47
0#
#48
b101 '
1#
#49
0#
#50
b110 '
1#
#51
0#
#52
b111 '
1#
#53
0#
#54
1"
1&
b1000 '
1#
#55
0#
#56
0"
0&
b1001 '
1#
#57
0#
#58
b1010 '
1#
#59
0#
#60
b1011 '
1#
#61
0#
#62
b1100 '
1#
#63
0#
#64
b1101 '
1#
#65
0#
#66
b1110 '
1#
