BitSampleCount.sv
///////////////////////////////////////////////////////////////////////////////
// Module: BitSampleCounter.sv
// Project: Extending a Simple Microprocessor
// References:
// Description: Counter for char detection.
// Implmentation: Implemented in behavioral verilog.
//
// TODO: Data is not being sent out. Check If else logic.
// Change history:
//
///////////////////////////////////////////////////////////////////////////////

module BitSampleCounter(output dataOut,
                        output idEnable,
                        input dataIn,
                        input [3:0] enable,
                        input clk);

    reg [3:0] count;
    reg startFlag;
    reg id;
    reg data;

    always @(posedge clk) begin
        if (enable == 4'b0000) begin
            startFlag <= 1'b1;
        end else if (startFlag && (count < 4'b1111)) begin
            startFlag <= 1'b1;
            count <= count + 1;
            data <= dataIn;
        end else begin
            id <= 1'b1;
            count <= 4'b0000;
            startFlag <= 1'b0;
        end

    end

    assign idEnable = id;
    assign dataOut = data;

endmodule

module BitSampleCounter_tb();
    // Inputs
    reg [3:0] enable;
    reg dataIn;
    reg clk;

    // Outputs
    wire dataOut;
    wire idEnable;





    BitSampleCounter bsc(dataOut,
                         idEnable,
                         dataIn,
                         enable,
                         clk);

    initial begin
    $dumpfile("BitSampleCounter_tb.vcd");
    $dumpvars;
    end
    // Set up the clock.
    parameter CLOCK_PERIOD=2;
    initial clk=1;
    initial enable = 0;
    initial dataIn = 0;
    always begin
       #(CLOCK_PERIOD/2);
       clk = ~clk;
    end



   // Set up the inputs to the design. Each line is a clock cycle.
    initial begin
    enable <= 0; dataIn <= 0; @(posedge clk);

    enable <= 1; dataIn <= 0; @(posedge clk);

    enable <= 4; dataIn <= 0; @(posedge clk);

    enable <= 7; dataIn <= 1; @(posedge clk);

    enable <= 1; dataIn <= 0; @(posedge clk);

    enable <= 0; dataIn <= 1; @(posedge clk);

    enable <= 0; dataIn <= 1; @(posedge clk);

    enable <= 0; dataIn <= 1; @(posedge clk);

    $finish;
    end
endmodule

BitSampleCounter_tb.vcd
$date
	Thu May 19 21:23:47 2016
$end
$version
	Icarus Verilog
$end
$timescale
	1s
$end
$scope module BitSampleCounter_tb $end
$var wire 1 ! idEnable $end
$var wire 1 " dataOut $end
$var reg 1 # clk $end
$var reg 1 $ dataIn $end
$var reg 4 % enable [3:0] $end
$scope module bsc $end
$var wire 1 # clk $end
$var wire 1 $ dataIn $end
$var wire 1 " dataOut $end
$var wire 4 & enable [3:0] $end
$var wire 1 ! idEnable $end
$var reg 4 ' count [3:0] $end
$var reg 1 ( data $end
$var reg 1 ) id $end
$var reg 1 * startFlag $end
$upscope $end
$upscope $end
$enddefinitions $end
#0
$dumpvars
1*
x)
x(
bx '
b0 &
b0 %
0$
1#
x"
x!
$end
#1
0#
#2
1#
#3
0#
#4
b1 %
b1 &
1#
#5
0#
#6
0*
b0 '
1!
1)
1#
#7
0#
#8
b100 %
b100 &
1#
#9
0#
#10
1#
#11
0#
#12
1$
b111 %
b111 &
1#
#13
0#
#14
1#
#15
0#
#16
0$
b1 %
b1 &
1#
#17
0#
#18
1#
#19
0#
#20
1$
b0 %
b0 &
1#
#21
0#
#22
1*
1#
