ShiftPToS.sv
///////////////////////////////////////////////////////////////////////////////
// Module: ShiftPToS.sv
// Project: Extending a Simple Microprocessor
// References:
// Description: Shifter that takes in an 8-bit parallel input and has 1-bit
// parallel output
// Implementation: Implemented in behavioral verilog.
//
// TODO: make a testbench. Do a sanity check.
// Change history:
//
///////////////////////////////////////////////////////////////////////////////

module ShiftPToS(output sOut,
                 input [9:0] data,
                 input sIn,
                 input load,
					  input SRControl
                 input Clock,
				 input rst);

    reg [9:0] temp;

    // always block entered on posedge of the clock or load.
    // if there load line has a value then temp is assigned to 8-bit data
    // else top bit of temp is taken off and sIn is appended to temp
    always @(posedge Clock) begin
		if (!rst)
			temp <= 10'bz;
		else if (load)
			temp <= data;
      else if (SRControl)
         temp <= {temp[8:0], sIn};
    end
    // assign sOut temp
    assign sOut = temp[9];

endmodule

module ShiftPToS_tb();
    // Inputs
    reg [9:0] data;
	reg rst;
    reg sIn;
    reg load;
    reg Clock;

    // Outputs
    wire sOut;

    ShiftPToS uut (sOut,
                   data,
                   sIn,
                   load,
                   Clock,
				   rst);

    initial begin
    $dumpfile("ShiftPToS_tb.vcd");
    $dumpvars;
    end
    // Set up the clock.
    parameter CLOCK_PERIOD=2;
    initial Clock=1;
    initial data = 0;
    initial sIn = 0;
    initial load = 0;
    always begin
       #(CLOCK_PERIOD/2);
       Clock = ~Clock;
    end



   // Set up the inputs to the design. Each line is a clock cycle.
    initial begin

    rst <= 0; @(posedge Clock); rst <= 1; @(posedge Clock);

    data <= 10'b1000010100; load <= 1; sIn <= 1;    @(posedge Clock);
                                                    @(posedge Clock);
                                                    @(posedge Clock);



                            load <= 0; sIn <= 0;	@(posedge Clock);
                                                    @(posedge Clock);
                                                    @(posedge Clock);


                            load <= 0; sIn <= 0;	@(posedge Clock);
                                                    @(posedge Clock);
                                                    @(posedge Clock);


                            load <= 0; sIn <= 1;    @(posedge Clock);
                                                    @(posedge Clock);
                                                    @(posedge Clock);

                            load <= 0; sIn <= 1;    @(posedge Clock);
                            load <= 1; sIn <= 1;    @(posedge Clock);

    $finish;
   end
endmodule

ShiftPToS_tb.vcd
$date
	Mon May 23 15:52:40 2016
$end
$version
	Icarus Verilog
$end
$timescale
	1s
$end
$scope module ShiftPToS_tb $end
$var wire 1 ! sOut $end
$var reg 1 " Clock $end
$var reg 10 # data [9:0] $end
$var reg 1 $ load $end
$var reg 1 % rst $end
$var reg 1 & sIn $end
$scope module uut $end
$var wire 1 " Clock $end
$var wire 10 ' data [9:0] $end
$var wire 1 $ load $end
$var wire 1 % rst $end
$var wire 1 & sIn $end
$var wire 1 ! sOut $end
$var reg 10 ( temp [9:0] $end
$upscope $end
$upscope $end
$enddefinitions $end
#0
$dumpvars
bx0 (
b0 '
0&
0%
0$
b0 #
1"
x!
$end
#1
0"
#2
z!
bz (
1%
1"
#3
0"
#4
1!
b1000010100 (
1&
1$
b1000010100 #
b1000010100 '
1"
#5
0"
#6
1"
#7
0"
#8
1"
#9
0"
#10
0&
0$
1"
#11
0"
#12
0!
b101000 (
1"
#13
0"
#14
b1010000 (
1"
#15
0"
#16
b10100000 (
1"
#17
0"
#18
b101000000 (
1"
#19
0"
#20
1!
b1010000000 (
1"
#21
0"
#22
0!
b100000000 (
1&
1"
#23
0"
#24
1!
b1000000001 (
1"
#25
0"
#26
0!
b11 (
1"
#27
0"
#28
b111 (
1"
#29
0"
#30
1!
b1000010100 (
1$
1"
