ShiftPToS.sv
///////////////////////////////////////////////////////////////////////////////
// Module: ShiftPToS.sv
// Project: Extending a Simple Microprocessor
// References:
// Description: Shifter that takes in an 8-bit parallel input and has 1-bit
// parallel output
// Implementation: Implemented in behavioral verilog.
//
// TODO: make a testbench. Do a sanity check.
// Change history:
//
///////////////////////////////////////////////////////////////////////////////

module ShiftPToS(output sOut,
                 input [7:0] data,
                 input sIn,
                 input load,
                 input Clock,
				 input rst);

    reg [7:0] temp;

    // always block entered on posedge of the clock or load.
    // if there load line has a value then temp is assigned to 8-bit data
    // else top bit of temp is taken off and sIn is appended to temp
    always @(posedge Clock or posedge load) begin
		if (!rst)
			temp <= 8'bz;
        else if (load)
            temp <= data;
        else
            temp <= {temp[6:0], sIn};
    end
    // assign sOut temp
    assign sOut = temp[7];

endmodule

module ShiftPToS_tb();
    // Inputs
    reg [7:0] data;
	reg rst;
    reg sIn;
    reg load;
    reg Clock;

    // Outputs
    wire sOut;

    ShiftPToS uut (sOut,
                   data,
                   sIn,
                   load,
                   Clock,
				   rst);

    initial begin
    $dumpfile("ShiftPToS_tb.vcd");
    $dumpvars;
    end
    // Set up the clock.
    parameter CLOCK_PERIOD=2;
    initial Clock=1;
    initial data = 0;
    initial sIn = 0;
    initial load = 0;
    always begin
       #(CLOCK_PERIOD/2);
       Clock = ~Clock;
    end



   // Set up the inputs to the design. Each line is a clock cycle.
    initial begin

    rst <= 0; @(posedge Clock); rst <= 1; @(posedge Clock);

    data <= 8'b10000101; load <= 1; sIn <= 1;   @(posedge Clock);
                                                @(posedge Clock);
                                                @(posedge Clock);



    data <= 8'b01111111; load <= 0; sIn <= 0;	@(posedge Clock);
                                                @(posedge Clock);
                                                @(posedge Clock);


    data <= 8'b10101010; load <= 1; sIn <= 0;	@(posedge Clock);
                                                @(posedge Clock);
                                                @(posedge Clock);


    data <= 8'b11010010; load <= 0; sIn <= 1;   @(posedge Clock);
                                                @(posedge Clock);
                                                @(posedge Clock);

    data <= 8'b00010001; load <= 1; sIn <= 1;   @(posedge Clock);
                         load <= 0; sIn <= 1;   @(posedge Clock);

    $finish;
   end
endmodule

ShiftPToS_tb.vcd
$date
	Sun May 22 17:12:15 2016
$end
$version
	Icarus Verilog
$end
$timescale
	1s
$end
$scope module ShiftPToS_tb $end
$var wire 1 ! sOut $end
$var reg 1 " Clock $end
$var reg 8 # data [7:0] $end
$var reg 1 $ load $end
$var reg 1 % rst $end
$var reg 1 & sIn $end
$scope module uut $end
$var wire 1 " Clock $end
$var wire 8 ' data [7:0] $end
$var wire 1 $ load $end
$var wire 1 % rst $end
$var wire 1 & sIn $end
$var wire 1 ! sOut $end
$var reg 8 ( temp [7:0] $end
$upscope $end
$upscope $end
$enddefinitions $end
#0
$dumpvars
bx0 (
b0 '
0&
0%
0$
b0 #
1"
x!
$end
#1
0"
#2
z!
bz (
1%
1"
#3
0"
#4
1!
b10000101 (
1&
1$
b10000101 #
b10000101 '
1"
#5
0"
#6
1"
#7
0"
#8
1"
#9
0"
#10
0&
0$
b1111111 #
b1111111 '
1"
#11
0"
#12
0!
b1010 (
1"
#13
0"
#14
b10100 (
1"
#15
0"
#16
1!
b10101010 (
1$
b10101010 #
b10101010 '
1"
#17
0"
#18
1"
#19
0"
#20
1"
#21
0"
#22
1&
0$
b11010010 #
b11010010 '
1"
#23
0"
#24
0!
b1010101 (
1"
#25
0"
#26
1!
b10101011 (
1"
#27
0"
#28
0!
b10001 (
1$
b10001 #
b10001 '
1"
#29
0"
#30
0$
1"
#31
0"
#32
b100011 (
1"
